QF3D.py
QF3D-1.0.dist-info/LICENSE
QF3D-1.0.dist-info/METADATA
QF3D-1.0.dist-info/WHEEL
QF3D-1.0.dist-info/top_level.txt
QF3D-1.0.dist-info/RECORD
