Metadata-Version: 2.1
Name: QF3D
Version: 1.0
Summary: 3D Feynman Diagram Visualizer
Author-email: Ali Hakim Taskiran <alihakimxyz@gmail.com>
License: MIT License
Project-URL: Homepage, https://github.com/alihakimtaskiran/QF3D
Project-URL: Bug Tracker, https://github.com/alihakimtaskiran/QF3D/issues
Classifier: Programming Language :: Python :: 3
Classifier: License :: OSI Approved :: MIT License
Classifier: Operating System :: OS Independent
Requires-Python: >=3.7
License-File: LICENSE
